Workbook

Sheet Оценка проекта
A1: Компонент | B1: Сумма, ₽
A2: Разработка + резерв | B2: ='Оценка стоимости'!E8 -> 14586880
A3: AI‑OPEX (Claude Opus + MiniMax) | B3: ='Оценка AI-OPEX'!E6 -> 1440772.7
A4: подытог | B4: =SUM(B2:B3) -> 16027653
A5: НДС 5% | B5: =B4*5% -> 801382.63
A6: ИТОГО проект MUST HAVE, руб | B6: =SUM(B4:B5) -> 16829035
A8: Объём: 118 требований ФТ, целевая архитектура CQRS, 46 клиник, 5442 врача.
A9: Не входит: миграция с 1С, аттестация ИСПДн, инфраструктура, лист ожидания, история лечения. См. лист «Не входит в объём».
A10: Срок по договору: 11,3 месяца — подготовка 1,5, разработка 6,8, опытная эксплуатация 3,0.
A11: Команда: 5 фуллстек-билдеров, 1 инженер внедрения, руководитель проекта на половине ставки.

Sheet Оценка стоимости
A1: Роль | B1: Уровень | C1: Часы | D1: Ставка (₽/ч) | E1: Стоимость (₽)
A2: Fullstack Builder | B2: Senior | C2: 2103 | D2: ='Ставки людей'!C2 -> 3600 | E2: =C2*D2 -> 7570800
A3: Fullstack Builder | B3: Приёмка и склейка | C3: 1045 | D3: ='Ставки людей'!C2 -> 3600 | E3: =C3*D3 -> 3762000
A4: Инженер внедрения | B4: Middle | C4: 175 | D4: ='Ставки людей'!C4 -> 1600 | E4: =C4*D4 -> 280000
A5: Руководитель проекта | B5: Senior | C5: 392 | D5: ='Ставки людей'!C5 -> 3600 | E5: =C5*D5 -> 1411200
A6: ИТОГО (средние ставки) | C6: =SUM(C2:C5) -> 3715 | E6: =SUM(E2:E5) -> 13024000
D7: резерв | E7: =E6*12% -> 1562880
D8: сумма с резервом | E8: =E6+E7 -> 14586880
A10: Резерв 12% — на изменение требований при 118 пунктах ФТ. Это не маржа.
A11: Себестоимость 12,3 млн ₽. При неизрасходованном резерве валовая маржа 23%.
A12: Ставка 3 600 ₽/ч — базовая для дополнительных работ по соглашениям сторон.

Sheet Оценка AI-OPEX
A1: Статья | B1: Период | C1: Сумма, $ | D1: Курс | E1: Сумма, ₽
A2: Claude Max ×5 (Opus как судья и приёмка) | B2: 8,3 мес работ | C2: 8300 | D2: 79.46 | E2: =C2*D2 -> 659518
A3: MiniMax 24/7 (основная генерация) | B3: 8,3 мес работ | C3: 6267 | D3: 79.46 | E3: =C3*D3 -> 497975.82
A4: Браузерный контур агентов, прокси | B4: 8,3 мес работ | C4: 1200 | D4: 79.46 | E4: =C4*D4 -> 95352
A5: Резерв на рост использования | B5: – | C5: =SUM(C2:C4)*15% -> 2365.05 | D5: 79.46 | E5: =C5*D5 -> 187926.87
A6: Итого AI‑OPEX | B6: – | C6: =SUM(C2:C5) -> 18132.05 | D6: 79.46 | E6: =C6*D6 -> 1440772.7
A8: Курс ЦБ РФ на 1 августа 2026. Подписки посчитаны на объём работ. Растяжку графика покрывает резерв 25%.

Sheet Оценка трудозатрат
A1: Этап / Модуль | B1: Ключевые задачи | C1: Оценка (часы) | D1: Основные исполнители
A2: 1. Фундамент и безопасность | B2: Каркас платформы, шаблоны сервисов, CI/CD в контуре заказчика, observability. | C2: 214 | D2: ИИ-агенты + Builder (ревью)
B3: Authn/authz, RBAC, шифрование ПДн при передаче и хранении, работа с секретами. | C3: 190 | D3: Builder, ИИ-агенты
B4: Zero-downtime, blue-green, миграции схемы без простоя под SLA 99,99%. | C4: 98 | D4: Builder
B5: Синтетические данные для dev/stage, обезличивание. | C5: 58 | D5: ИИ-агенты
A6: 2. Administration (НСИ) | B6: Услуги и цены, врачи с мультиспециализацией, специальности и синонимы, клиники и кабинеты. | C6: 96 | D6: ИИ-агенты + Builder (ревью)
B7: Матрица «врач — услуга — оборудование», правила длительности, связанные и обязательные услуги. | C7: 147 | D7: Builder, ИИ-агенты
B8: Репликация картотеки пациентов из МИС. | C8: 39 | D8: ИИ-агенты
A9: 3. Schedule (сетка) | B9: Создание и копирование расписаний врачей и оборудования, отсутствия, праздники, блокировки. | C9: 88 | D9: ИИ-агенты
B10: Зависимые расписания (работа в паре, оборудование как ресурс), снос расписания с перезаписью. | C10: 95 | D10: Builder, ИИ-агенты
B11: Просмотр сетки с записями, оптимизация отклика до 1 секунды. | C11: 36 | D11: Builder
A12: 4. Timeslots | B12: Движок нарезки слотов: произвольная длительность, техперерывы, ВНД. | C12: 55 | D12: Builder, ИИ-агенты
B13: Read-модель, денормализация, синхронизация write→read не более 5 секунд. | C13: 69 | D13: Builder
B14: Поиск свободных слотов до 0,5 секунды, индексы и оптимизация под 200+ RPS. | C14: 222 | D14: Builder
A15: 5. Appointment (запись) | B15: Доменная модель записи, статусы, история, проверка доступности всех ресурсов на всё время услуги. | C15: 95 | D15: Builder, ИИ-агенты
B16: Многослотовые записи, сценарии брони оборудования, пересечения, первичные слоты, маломобильные. | C16: 95 | D16: ИИ-агенты + Builder
B17: Отмена и перенос, проверка предшествующих услуг, бронь слота с TTL. | C17: 95 | D17: ИИ-агенты + Builder
B18: Конкурентность, идемпотентность, черновики записи при отказе сервиса. | C18: 95 | D18: Builder
A19: 6. Клиенты | B19: Проекция картотеки, контакты, подтверждение телефона, записи и заявки пациента. | C19: 17 | D19: ИИ-агенты
A20: 8. Cross-cutting | B20: RBAC по площадкам, аудит изменений с глубиной хранения 2–3 года. | C20: 21 | D20: ИИ-агенты
A21: 9. Фронтенд | B21: Дизайн-система из design.md, макеты всех экранов, сборка базового АРМ. | C21: 49 | D21: Claude Design + Builder
A22: 10. Интеграции | B22: Schedule API Gateway и Timeslots API Gateway в DMZ, публикация контрактов, rate limit. | C22: 11 | D22: Builder
A23: 11. Документация | B23: Контракты API и эксплуатационная документация — только то, что заказчик назвал прямо. | C23: 13 | D23: ИИ-агенты
A24: 12. Приёмка | B24: Нагрузочные прогоны: 2 цикла оптимизации под 200 RPS и целевые отклики. | C24: 100 | D24: Builder
B25: Автоматический набор проверок соответствия по 118 требованиям ФТ, отчёт по кнопке. | C25: 105 | D25: ИИ-агенты + Builder
B26: Выборочная человеческая приёмка требований: то, что харнесс не ловит. | C26: 525 | D26: Builder
B27: Приёмо-сдаточные испытания на одном филиале. | C27: 83 | D27: Инженер внедрения
A28: 13. Передача | B28: Передача артефактов и знаний по итогам опытной эксплуатации. | C28: 92 | D28: Инженер внедрения
A29: 14. Оркестрация | B29: Инженерия контекста и графа задач, разбор брака и конфликтов между агентами. | C29: 520 | D29: Builder
A30: 15. Управление проектом | B30: Согласования с заказчиком, акты, приёмочные процедуры, отчётность. | C30: 392 | D30: Руководитель проекта
A31: Итого: | C31: =SUM(C2:C30) -> 3715
B33: Часы — человеческие. Машинное время агентов в них не входит: оно учтено на листе «Оценка AI-OPEX».

Sheet Роли
A1: Роль | B1: Уровень | C1: Часы | D1: % от проекта
A2: Fullstack Builder (разработка и ядро) | B2: Senior | C2: 2103 | D2: =C2/$C$6 -> 0.56608345
A3: Fullstack Builder (приёмка, оркестрация) | B3: Senior | C3: 1045 | D3: =C3/$C$6 -> 0.28129206
A4: Инженер внедрения (ПСИ, передача) | B4: Middle | C4: 175 | D4: =C4/$C$6 -> 0.047106326
A5: Руководитель проекта | B5: Senior | C5: 392 | D5: =C5/$C$6 -> 0.10551817
A6: ИТОГО | C6: =SUM(C2:C5) -> 3715 | D6: =SUM(D2:D5) -> 1
A8: Ролей четыре вместо двенадцати: тестирование, аналитика, документация и дизайн выполняются агентами.

Sheet Ставки людей
A1: Роль | B1: Уровень | C1: Средняя
A2: Fullstack Builder | B2: Senior | C2: 3600
A3: Fullstack Builder | B3: Приёмка и склейка | C3: 3600
A4: Инженер внедрения | B4: Middle | C4: 1600
A5: Руководитель проекта | B5: Senior | C5: 3600
A7: Свои лояльные разработчики, фиксированная почасовка. Себестоимость билдера 3 000 ₽/ч, инженера внедрения 1 250 ₽/ч.

Sheet Не входит в объём
A1: Работа | B1: Часы по классической оценке | C1: Основание
A2: Лист ожидания и заявки: автоподбор, автопредложение, улучшение даты | B2: 136 | C2: Вынесено во второй этап. FAQ: «автоматизированный подбор обсуждаемо с MVP» — заказчик сам допускает перенос
A3: История лечения: повторный визит, связанные визиты, контроль сроков | B3: 39 | C3: Вынесено во второй этап. Не входит в ядро записи
A4: Опытная эксплуатация: первая линия подрядчика | B4: 1535 | C4: Не убрана, а переведена на почасовую оплату по факту заявок: 1 535 ч × 1 600 ₽ = 2 456 000 ₽ при полной выборке. Объём обращений заранее неизвестен, фиксировать его невыгодно обеим сторонам
A5: Нагрузочное тестирование: циклы 3–5 | B5: 65 | C5: Сокращено до двух циклов. Остальные — в период опытной эксплуатации, на реальном профиле
A6: Миграция с 1С: реверс-инжиниринг Schedule и Appointment, маршруты WSO2 | B6: 1579 | C6: Требования на миграцию нет ни в ФТ, ни в FAQ. В концепции целевой архитектуры миграция названа риском на слайде «последствия», объём не задан
A7: Перенос исторических данных, ETL | B7: 526 | C7: Требования нет
A8: Двусторонняя синхронизация на переходный период | B8: 702 | C8: Требования на параллельную работу двух систем нет
A9: Реконсиляция, отчёты расхождений, прогоны переключения | B9: 392 | C9: Вычеркнуто вместе с миграцией
A10: Выверка и чистка НСИ из 1С | B10: 486 | C10: Требования нет
A11: Волны cutover по 46 клиникам, откаты | B11: 1522 | C11: Требования нет
A12: Аттестация ИСПДн, пентест, СКЗИ | B12: 820 | C12: Слово «аттестация» встречается в рефах один раз — в нашем же вопросе заказчику. Его ответ: «если будут реальные данные – то 152-ФЗ должно выполняться, ПДн шифровать при передаче и хранении». Шифрование входит в объём, аттестация — нет
A13: Стенды, нагрузочный контур, DR-площадка | B13: — | C13: FAQ п.4: «Кто отвечает за инфраструктуру, Kubernetes, Helm-чарты?» — «Департамент инфраструктуры заказчика». Подрядчик катит только в dev
A14: Доработка систем-потребителей | B14: — | C14: FAQ: «внешние потребители должны будут переработать интеграции». Наше — опубликовать API
A15: Интеграция с Базой знаний | B15: — | C15: FAQ: «Базу Знаний в целевом решении не используем»
A16: Маркетинговые рассылки, уведомления по анализам | B16: — | C16: FAQ: «не входит в MVP, реализуется в рамках отдельного сервиса»
A17: Автоматический оптимизатор маршрута в корзине | B17: — | C17: FAQ: «В MVP автоматический оптимизатор не закладываем», нужна только возможность на будущее
A18: Обучение сотрудников заказчика | B18: 422 | C18: В концепции заказчика снижение затрат на обучение — их выгода от проекта, а не обязанность подрядчика
A19: ИТОГО снято | B19: =SUM(B2:B18) -> 8224 | C19: Миграцию и аттестацию предлагать отдельными этапами по отдельному ТЗ, а не растворять в цене.

Sheet График
A1: Фаза | B1: Длительность | C1: Что происходит
A2: Подготовка | B2: 1,5 мес | C2: Техническое задание по 118 требованиям, получение доступов к контурам заказчика, целевая архитектура и ADR
A3: Разработка | B3: 6,8 мес | C3: Пять билдеров и агентная фабрика. Объём работ — 3 715 человеко-часов
A4: Опытная эксплуатация | B4: 3,0 мес | C4: Первая линия подрядчика оплачивается отдельно, по факту заявок
A5: СРОК ПО ДОГОВОРУ | B5: 11,3 мес
A7: Про темп работы
A8: Объём работ — 3 715 человеко-часов, 16 829 035 ₽ с НДС.
A9: График рассчитан на ровный темп без переработок, а не на предельную загрузку команды.
A10: Оплата почасовая: срок сам по себе на стоимость не влияет.
A12: Почему график такой
A13: Узкое место в агентной разработке — не генерация кода, а человеческая приёмка требований.
A14: Именно её качество падает от спешки первым, а стоимость пропущенного дефекта в системе записи
A15: на 46 клиник несопоставима со стоимостью лишнего месяца в графике.
A17: Поэтому график построен под ровный темп. Если работа пойдёт быстрее, проект сдаётся раньше срока —
A18: единственный вид сюрприза, который заказчику нравится.
